apdtflow/__init__.py
apdtflow/augmentation.py
apdtflow/cli.py
apdtflow/conformal.py
apdtflow/cv_factory.py
apdtflow/data.py
apdtflow/exogenous.py
apdtflow/forecaster.py
apdtflow/inference.py
apdtflow/logger_util.py
apdtflow/preprocessing.py
apdtflow/training.py
apdtflow/utils.py
apdtflow/evaluation/__init__.py
apdtflow/evaluation/metric_factory.py
apdtflow/evaluation/regression_evaluator.py
apdtflow/models/__init__.py
apdtflow/models/apdtflow.py
apdtflow/models/base_forecaster.py
apdtflow/models/decoder.py
apdtflow/models/dynamic_dilation_conv.py
apdtflow/models/dynamics.py
apdtflow/models/embedding.py
apdtflow/models/ensemble_forecaster.py
apdtflow/models/fusion.py
apdtflow/models/multi_scale_decomposer.py
apdtflow/models/tcn_forecaster.py
apdtflow/models/transformer_forecaster.py
apdtflow/preprocessing/__init__.py
apdtflow/preprocessing/categorical_encoder.py
tests/__init__.py
tests/test_augmentation.py
tests/test_backtesting.py
tests/test_categorical_encoder.py
tests/test_categorical_integration.py
tests/test_cli.py
tests/test_conformal.py
tests/test_cv.py
tests/test_data.py
tests/test_dynamic_dilation_conv.py
tests/test_dynamics.py
tests/test_embedding.py
tests/test_ensemble_forecaster.py
tests/test_evaluation.py
tests/test_exog_conformal_integration.py
tests/test_exogenous.py
tests/test_forecaster_api.py
tests/test_fusion.py
tests/test_inference.py
tests/test_integration.py
tests/test_logger_util.py
tests/test_metric_factory.py
tests/test_models.py
tests/test_multi_scale_decomposer.py
tests/test_residual_analysis.py
tests/test_tcn_forecaster.py
tests/test_training.py
tests/test_transformer_forecaster.py
tests/test_utils.py
apdtflow-0.3.0.dist-info/License
apdtflow-0.3.0.dist-info/METADATA
apdtflow-0.3.0.dist-info/WHEEL
apdtflow-0.3.0.dist-info/entry_points.txt
apdtflow-0.3.0.dist-info/top_level.txt
apdtflow-0.3.0.dist-info/RECORD
