Metadata-Version: 2.2
Name: apdtflow
Version: 0.3.0
Summary: APDTFlow: A modular forecasting framework for time series data
Home-page: https://github.com/yotambraun/APDTFlow
Author: Yotam Barun
Author-email: Yotam Barun <yotambarun93@gmail.com>
License: MIT
Project-URL: Homepage, https://github.com/yotambraun/APDTFlow
Project-URL: Documentation, https://github.com/yotambraun/APDTFlow
Project-URL: Source, https://github.com/yotambraun/APDTFlow
Keywords: time-series,forecasting,neural-ode,deep-learning,transformer,tcn,timeseries-analysis,time-series-forecasting,neural-differential-equations,probabilistic-forecasting,uncertainty-quantification,multi-scale-decomposition,pytorch,machine-learning
Classifier: Development Status :: 4 - Beta
Classifier: Intended Audience :: Science/Research
Classifier: Intended Audience :: Developers
Classifier: Topic :: Scientific/Engineering :: Artificial Intelligence
Classifier: Topic :: Scientific/Engineering :: Information Analysis
Classifier: Programming Language :: Python :: 3
Classifier: Programming Language :: Python :: 3.10
Classifier: Programming Language :: Python :: 3.11
Classifier: Programming Language :: Python :: 3.12
Classifier: Operating System :: OS Independent
Classifier: License :: OSI Approved :: MIT License
Requires-Python: >=3.10
License-File: License
Requires-Dist: torch
Requires-Dist: torchdiffeq
Requires-Dist: pandas
Requires-Dist: numpy
Requires-Dist: matplotlib
Requires-Dist: scipy
Requires-Dist: tensorboard
Requires-Dist: pyyaml
Requires-Dist: scikit-learn
Requires-Dist: statsmodels
Requires-Dist: tqdm
Dynamic: author
Dynamic: home-page
Dynamic: requires-python
